{
	"class" : {
		 },
	"instance" : {
		"render:" : "pm 4/8/2023 13:16",
		"renderArp:" : "pm 4/12/2023 17:14",
		"renderBass:" : "pm 4/12/2023 17:12",
		"renderBassFast:" : "pm 4/12/2023 17:12",
		"renderBassSlow:" : "pm 4/12/2023 17:13",
		"renderDrumsHiHat:" : "pm 4/12/2023 16:17",
		"renderDrumsKick:" : "pm 4/12/2023 16:01",
		"renderDrumsSnare:" : "pm 4/12/2023 16:05",
		"renderDrumsTom:" : "pm 4/12/2023 16:14",
		"renderLead:" : "pm 4/12/2023 17:16",
		"renderPad:" : "pm 3/29/2023 20:59",
		"renderPadOctaves:" : "pm 4/12/2023 16:24",
		"renderPadSteps:" : "pm 4/12/2023 16:59" } }
